README.rst
pytest_http_mocker.py
setup.py
pytest_http_mocker.egg-info/PKG-INFO
pytest_http_mocker.egg-info/SOURCES.txt
pytest_http_mocker.egg-info/dependency_links.txt
pytest_http_mocker.egg-info/entry_points.txt
pytest_http_mocker.egg-info/requires.txt
pytest_http_mocker.egg-info/top_level.txt